extension/__init__.py
extension/_interface.py
extension/_runner.py
extension/_utils.py
extension/_version.py
extension/constants.py
extension/interface.py
extension/runner.py
extension/utils.py
extensionlib-0.1.0.dist-info/METADATA
extensionlib-0.1.0.dist-info/WHEEL
extensionlib-0.1.0.dist-info/entry_points.txt
extensionlib-0.1.0.dist-info/license_files/LICENSE.txt
extensionlib-0.1.0.dist-info/RECORD
