Metadata-Version: 2.1
Name: extensionlib
Version: 0.1.0
Summary: The toolkit for building extension modules
Project-URL: History, https://ofek.dev/extensionlib/history/
Project-URL: Homepage, https://ofek.dev/extensionlib/
Project-URL: Source, https://github.com/ofek/extensionlib
Project-URL: Tracker, https://github.com/ofek/extensionlib/issues
Author-email: Ofek Lev <oss@ofek.dev>, Henry Schreiner <henryfs@princeton.edu>
License: MIT
Classifier: Development Status :: 3 - Alpha
Classifier: Intended Audience :: Developers
Classifier: License :: OSI Approved :: MIT License
Classifier: Natural Language :: English
Classifier: Operating System :: OS Independent
Classifier: Programming Language :: Python :: 3.10
Classifier: Programming Language :: Python :: 3.11
Classifier: Programming Language :: Python :: 3.7
Classifier: Programming Language :: Python :: 3.8
Classifier: Programming Language :: Python :: 3.9
Classifier: Programming Language :: Python :: Implementation :: CPython
Classifier: Programming Language :: Python :: Implementation :: PyPy
Classifier: Topic :: Software Development :: Build Tools
Requires-Python: >=3.7
Requires-Dist: importlib-metadata; python_version < '3.8'
